diskspacemon/__init__.py
diskspacemon/__main__.py
diskspacemon/__version__.py
diskspacemon/monitor.ini
diskspacemon/monitor.py
diskspacemon/syslogx.py
diskspacemon-0.19.dist-info/METADATA
diskspacemon-0.19.dist-info/WHEEL
diskspacemon-0.19.dist-info/entry_points.txt
diskspacemon-0.19.dist-info/top_level.txt
diskspacemon-0.19.dist-info/RECORD
